[
    {
        "id": 1,
        "name": "aten::to",
        "start_time": 1757354705982695026,
        "end_time": 1757354705982917326,
        "is_leaf": true,
        "scope": "forward",
        "parent": null,
        "children": []
    },
    {
        "id": 3,
        "name": "aten::to",
        "start_time": 1757354705982951226,
        "end_time": 1757354705983028226,
        "is_leaf": true,
        "scope": "forward",
        "parent": null,
        "children": []
    },
    {
        "id": 4,
        "name": "nn.Module: ResNet_0",
        "start_time": 1757354705983039826,
        "end_time": 1757354705985735526,
        "is_leaf": false,
        "scope": "forward",
        "parent": null,
        "children": [
            5,
            7,
            10,
            12,
            14,
            31,
            54,
            77,
            100,
            102,
            103
        ]
    },
    {
        "id": 5,
        "name": "nn.Module: Conv2d_0",
        "start_time": 1757354705983058226,
        "end_time": 1757354705983132726,
        "is_leaf": false,
        "scope": "forward",
        "parent": 4,
        "children": [
            6
        ]
    },
    {
        "id": 6,
        "name": "aten::conv2d",
        "start_time": 1757354705983072326,
        "end_time": 1757354705983130426,
        "is_leaf": true,
        "scope": "forward",
        "parent": 5,
        "children": []
    },
    {
        "id": 7,
        "name": "nn.Module: BatchNorm2d_0",
        "start_time": 1757354705983139726,
        "end_time": 1757354705983732926,
        "is_leaf": false,
        "scope": "forward",
        "parent": 4,
        "children": [
            8,
            9
        ]
    },
    {
        "id": 8,
        "name": "aten::add_",
        "start_time": 1757354705983164026,
        "end_time": 1757354705983172026,
        "is_leaf": true,
        "scope": "forward",
        "parent": 7,
        "children": []
    },
    {
        "id": 9,
        "name": "aten::batch_norm",
        "start_time": 1757354705983343826,
        "end_time": 1757354705983724926,
        "is_leaf": true,
        "scope": "forward",
        "parent": 7,
        "children": []
    },
    {
        "id": 10,
        "name": "nn.Module: ReLU_0",
        "start_time": 1757354705983748726,
        "end_time": 1757354705983817826,
        "is_leaf": false,
        "scope": "forward",
        "parent": 4,
        "children": [
            11
        ]
    },
    {
        "id": 11,
        "name": "aten::relu_",
        "start_time": 1757354705983780926,
        "end_time": 1757354705983813426,
        "is_leaf": true,
        "scope": "forward",
        "parent": 10,
        "children": []
    },
    {
        "id": 12,
        "name": "nn.Module: MaxPool2d_0",
        "start_time": 1757354705983827826,
        "end_time": 1757354705983984326,
        "is_leaf": false,
        "scope": "forward",
        "parent": 4,
        "children": [
            13
        ]
    },
    {
        "id": 13,
        "name": "aten::max_pool2d",
        "start_time": 1757354705983857026,
        "end_time": 1757354705983977126,
        "is_leaf": true,
        "scope": "forward",
        "parent": 12,
        "children": []
    },
    {
        "id": 14,
        "name": "nn.Module: Sequential_0",
        "start_time": 1757354705983994426,
        "end_time": 1757354705984359126,
        "is_leaf": false,
        "scope": "forward",
        "parent": 4,
        "children": [
            15
        ]
    },
    {
        "id": 15,
        "name": "nn.Module: BasicBlock_0",
        "start_time": 1757354705984006826,
        "end_time": 1757354705984358426,
        "is_leaf": false,
        "scope": "forward",
        "parent": 14,
        "children": [
            16,
            18,
            21,
            23,
            25,
            28,
            29
        ]
    },
    {
        "id": 16,
        "name": "nn.Module: Conv2d_1",
        "start_time": 1757354705984016026,
        "end_time": 1757354705984081026,
        "is_leaf": false,
        "scope": "forward",
        "parent": 15,
        "children": [
            17
        ]
    },
    {
        "id": 17,
        "name": "aten::conv2d",
        "start_time": 1757354705984029226,
        "end_time": 1757354705984078526,
        "is_leaf": true,
        "scope": "forward",
        "parent": 16,
        "children": []
    },
    {
        "id": 18,
        "name": "nn.Module: BatchNorm2d_1",
        "start_time": 1757354705984087826,
        "end_time": 1757354705984187726,
        "is_leaf": false,
        "scope": "forward",
        "parent": 15,
        "children": [
            19,
            20
        ]
    },
    {
        "id": 19,
        "name": "aten::add_",
        "start_time": 1757354705984102726,
        "end_time": 1757354705984110726,
        "is_leaf": true,
        "scope": "forward",
        "parent": 18,
        "children": []
    },
    {
        "id": 20,
        "name": "aten::batch_norm",
        "start_time": 1757354705984128626,
        "end_time": 1757354705984185626,
        "is_leaf": true,
        "scope": "forward",
        "parent": 18,
        "children": []
    },
    {
        "id": 21,
        "name": "nn.Module: ReLU_1",
        "start_time": 1757354705984190626,
        "end_time": 1757354705984213326,
        "is_leaf": false,
        "scope": "forward",
        "parent": 15,
        "children": [
            22
        ]
    },
    {
        "id": 22,
        "name": "aten::relu_",
        "start_time": 1757354705984197026,
        "end_time": 1757354705984211626,
        "is_leaf": true,
        "scope": "forward",
        "parent": 21,
        "children": []
    },
    {
        "id": 23,
        "name": "nn.Module: Conv2d_2",
        "start_time": 1757354705984216326,
        "end_time": 1757354705984263826,
        "is_leaf": false,
        "scope": "forward",
        "parent": 15,
        "children": [
            24
        ]
    },
    {
        "id": 24,
        "name": "aten::conv2d",
        "start_time": 1757354705984224126,
        "end_time": 1757354705984261426,
        "is_leaf": true,
        "scope": "forward",
        "parent": 23,
        "children": []
    },
    {
        "id": 25,
        "name": "nn.Module: BatchNorm2d_2",
        "start_time": 1757354705984267126,
        "end_time": 1757354705984332126,
        "is_leaf": false,
        "scope": "forward",
        "parent": 15,
        "children": [
            26,
            27
        ]
    },
    {
        "id": 26,
        "name": "aten::add_",
        "start_time": 1757354705984274826,
        "end_time": 1757354705984278926,
        "is_leaf": true,
        "scope": "forward",
        "parent": 25,
        "children": []
    },
    {
        "id": 27,
        "name": "aten::batch_norm",
        "start_time": 1757354705984289226,
        "end_time": 1757354705984330426,
        "is_leaf": true,
        "scope": "forward",
        "parent": 25,
        "children": []
    },
    {
        "id": 28,
        "name": "aten::add_",
        "start_time": 1757354705984335326,
        "end_time": 1757354705984341826,
        "is_leaf": true,
        "scope": "forward",
        "parent": 15,
        "children": []
    },
    {
        "id": 29,
        "name": "nn.Module: ReLU_1",
        "start_time": 1757354705984344726,
        "end_time": 1757354705984358026,
        "is_leaf": false,
        "scope": "forward",
        "parent": 15,
        "children": [
            30
        ]
    },
    {
        "id": 30,
        "name": "aten::relu_",
        "start_time": 1757354705984349026,
        "end_time": 1757354705984356626,
        "is_leaf": true,
        "scope": "forward",
        "parent": 29,
        "children": []
    },
    {
        "id": 31,
        "name": "nn.Module: Sequential_1",
        "start_time": 1757354705984361826,
        "end_time": 1757354705984793826,
        "is_leaf": false,
        "scope": "forward",
        "parent": 4,
        "children": [
            32
        ]
    },
    {
        "id": 32,
        "name": "nn.Module: BasicBlock_1",
        "start_time": 1757354705984366026,
        "end_time": 1757354705984793326,
        "is_leaf": false,
        "scope": "forward",
        "parent": 31,
        "children": [
            33,
            35,
            38,
            40,
            42,
            45,
            51,
            52
        ]
    },
    {
        "id": 33,
        "name": "nn.Module: Conv2d_3",
        "start_time": 1757354705984370526,
        "end_time": 1757354705984420926,
        "is_leaf": false,
        "scope": "forward",
        "parent": 32,
        "children": [
            34
        ]
    },
    {
        "id": 34,
        "name": "aten::conv2d",
        "start_time": 1757354705984377026,
        "end_time": 1757354705984419126,
        "is_leaf": true,
        "scope": "forward",
        "parent": 33,
        "children": []
    },
    {
        "id": 35,
        "name": "nn.Module: BatchNorm2d_3",
        "start_time": 1757354705984425426,
        "end_time": 1757354705984494326,
        "is_leaf": false,
        "scope": "forward",
        "parent": 32,
        "children": [
            36,
            37
        ]
    },
    {
        "id": 36,
        "name": "aten::add_",
        "start_time": 1757354705984432726,
        "end_time": 1757354705984436126,
        "is_leaf": true,
        "scope": "forward",
        "parent": 35,
        "children": []
    },
    {
        "id": 37,
        "name": "aten::batch_norm",
        "start_time": 1757354705984448626,
        "end_time": 1757354705984492726,
        "is_leaf": true,
        "scope": "forward",
        "parent": 35,
        "children": []
    },
    {
        "id": 38,
        "name": "nn.Module: ReLU_2",
        "start_time": 1757354705984506126,
        "end_time": 1757354705984520526,
        "is_leaf": false,
        "scope": "forward",
        "parent": 32,
        "children": [
            39
        ]
    },
    {
        "id": 39,
        "name": "aten::relu_",
        "start_time": 1757354705984510626,
        "end_time": 1757354705984519126,
        "is_leaf": true,
        "scope": "forward",
        "parent": 38,
        "children": []
    },
    {
        "id": 40,
        "name": "nn.Module: Conv2d_4",
        "start_time": 1757354705984522926,
        "end_time": 1757354705984568226,
        "is_leaf": false,
        "scope": "forward",
        "parent": 32,
        "children": [
            41
        ]
    },
    {
        "id": 41,
        "name": "aten::conv2d",
        "start_time": 1757354705984528926,
        "end_time": 1757354705984566526,
        "is_leaf": true,
        "scope": "forward",
        "parent": 40,
        "children": []
    },
    {
        "id": 42,
        "name": "nn.Module: BatchNorm2d_4",
        "start_time": 1757354705984571426,
        "end_time": 1757354705984664926,
        "is_leaf": false,
        "scope": "forward",
        "parent": 32,
        "children": [
            43,
            44
        ]
    },
    {
        "id": 43,
        "name": "aten::add_",
        "start_time": 1757354705984578426,
        "end_time": 1757354705984581926,
        "is_leaf": true,
        "scope": "forward",
        "parent": 42,
        "children": []
    },
    {
        "id": 44,
        "name": "aten::batch_norm",
        "start_time": 1757354705984593826,
        "end_time": 1757354705984663426,
        "is_leaf": true,
        "scope": "forward",
        "parent": 42,
        "children": []
    },
    {
        "id": 45,
        "name": "nn.Module: Sequential_2",
        "start_time": 1757354705984668026,
        "end_time": 1757354705984768626,
        "is_leaf": false,
        "scope": "forward",
        "parent": 32,
        "children": [
            46,
            48
        ]
    },
    {
        "id": 46,
        "name": "nn.Module: Conv2d_5",
        "start_time": 1757354705984672626,
        "end_time": 1757354705984706726,
        "is_leaf": false,
        "scope": "forward",
        "parent": 45,
        "children": [
            47
        ]
    },
    {
        "id": 47,
        "name": "aten::conv2d",
        "start_time": 1757354705984679326,
        "end_time": 1757354705984705026,
        "is_leaf": true,
        "scope": "forward",
        "parent": 46,
        "children": []
    },
    {
        "id": 48,
        "name": "nn.Module: BatchNorm2d_5",
        "start_time": 1757354705984708826,
        "end_time": 1757354705984768026,
        "is_leaf": false,
        "scope": "forward",
        "parent": 45,
        "children": [
            49,
            50
        ]
    },
    {
        "id": 49,
        "name": "aten::add_",
        "start_time": 1757354705984715326,
        "end_time": 1757354705984718826,
        "is_leaf": true,
        "scope": "forward",
        "parent": 48,
        "children": []
    },
    {
        "id": 50,
        "name": "aten::batch_norm",
        "start_time": 1757354705984727826,
        "end_time": 1757354705984766626,
        "is_leaf": true,
        "scope": "forward",
        "parent": 48,
        "children": []
    },
    {
        "id": 51,
        "name": "aten::add_",
        "start_time": 1757354705984771026,
        "end_time": 1757354705984776226,
        "is_leaf": true,
        "scope": "forward",
        "parent": 32,
        "children": []
    },
    {
        "id": 52,
        "name": "nn.Module: ReLU_2",
        "start_time": 1757354705984778826,
        "end_time": 1757354705984791526,
        "is_leaf": false,
        "scope": "forward",
        "parent": 32,
        "children": [
            53
        ]
    },
    {
        "id": 53,
        "name": "aten::relu_",
        "start_time": 1757354705984782726,
        "end_time": 1757354705984789926,
        "is_leaf": true,
        "scope": "forward",
        "parent": 52,
        "children": []
    },
    {
        "id": 54,
        "name": "nn.Module: Sequential_3",
        "start_time": 1757354705984796026,
        "end_time": 1757354705985198426,
        "is_leaf": false,
        "scope": "forward",
        "parent": 4,
        "children": [
            55
        ]
    },
    {
        "id": 55,
        "name": "nn.Module: BasicBlock_2",
        "start_time": 1757354705984799226,
        "end_time": 1757354705985198026,
        "is_leaf": false,
        "scope": "forward",
        "parent": 54,
        "children": [
            56,
            58,
            61,
            63,
            65,
            68,
            74,
            75
        ]
    },
    {
        "id": 56,
        "name": "nn.Module: Conv2d_6",
        "start_time": 1757354705984802726,
        "end_time": 1757354705984847726,
        "is_leaf": false,
        "scope": "forward",
        "parent": 55,
        "children": [
            57
        ]
    },
    {
        "id": 57,
        "name": "aten::conv2d",
        "start_time": 1757354705984808826,
        "end_time": 1757354705984845826,
        "is_leaf": true,
        "scope": "forward",
        "parent": 56,
        "children": []
    },
    {
        "id": 58,
        "name": "nn.Module: BatchNorm2d_6",
        "start_time": 1757354705984851126,
        "end_time": 1757354705984934426,
        "is_leaf": false,
        "scope": "forward",
        "parent": 55,
        "children": [
            59,
            60
        ]
    },
    {
        "id": 59,
        "name": "aten::add_",
        "start_time": 1757354705984857626,
        "end_time": 1757354705984861126,
        "is_leaf": true,
        "scope": "forward",
        "parent": 58,
        "children": []
    },
    {
        "id": 60,
        "name": "aten::batch_norm",
        "start_time": 1757354705984870626,
        "end_time": 1757354705984932926,
        "is_leaf": true,
        "scope": "forward",
        "parent": 58,
        "children": []
    },
    {
        "id": 61,
        "name": "nn.Module: ReLU_3",
        "start_time": 1757354705984936326,
        "end_time": 1757354705984950226,
        "is_leaf": false,
        "scope": "forward",
        "parent": 55,
        "children": [
            62
        ]
    },
    {
        "id": 62,
        "name": "aten::relu_",
        "start_time": 1757354705984940326,
        "end_time": 1757354705984948626,
        "is_leaf": true,
        "scope": "forward",
        "parent": 61,
        "children": []
    },
    {
        "id": 63,
        "name": "nn.Module: Conv2d_7",
        "start_time": 1757354705984952526,
        "end_time": 1757354705984989126,
        "is_leaf": false,
        "scope": "forward",
        "parent": 55,
        "children": [
            64
        ]
    },
    {
        "id": 64,
        "name": "aten::conv2d",
        "start_time": 1757354705984958026,
        "end_time": 1757354705984987326,
        "is_leaf": true,
        "scope": "forward",
        "parent": 63,
        "children": []
    },
    {
        "id": 65,
        "name": "nn.Module: BatchNorm2d_7",
        "start_time": 1757354705984991826,
        "end_time": 1757354705985066326,
        "is_leaf": false,
        "scope": "forward",
        "parent": 55,
        "children": [
            66,
            67
        ]
    },
    {
        "id": 66,
        "name": "aten::add_",
        "start_time": 1757354705984998026,
        "end_time": 1757354705985001126,
        "is_leaf": true,
        "scope": "forward",
        "parent": 65,
        "children": []
    },
    {
        "id": 67,
        "name": "aten::batch_norm",
        "start_time": 1757354705985009726,
        "end_time": 1757354705985064726,
        "is_leaf": true,
        "scope": "forward",
        "parent": 65,
        "children": []
    },
    {
        "id": 68,
        "name": "nn.Module: Sequential_4",
        "start_time": 1757354705985068826,
        "end_time": 1757354705985170826,
        "is_leaf": false,
        "scope": "forward",
        "parent": 55,
        "children": [
            69,
            71
        ]
    },
    {
        "id": 69,
        "name": "nn.Module: Conv2d_8",
        "start_time": 1757354705985075326,
        "end_time": 1757354705985103926,
        "is_leaf": false,
        "scope": "forward",
        "parent": 68,
        "children": [
            70
        ]
    },
    {
        "id": 70,
        "name": "aten::conv2d",
        "start_time": 1757354705985081126,
        "end_time": 1757354705985102526,
        "is_leaf": true,
        "scope": "forward",
        "parent": 69,
        "children": []
    },
    {
        "id": 71,
        "name": "nn.Module: BatchNorm2d_8",
        "start_time": 1757354705985106026,
        "end_time": 1757354705985170326,
        "is_leaf": false,
        "scope": "forward",
        "parent": 68,
        "children": [
            72,
            73
        ]
    },
    {
        "id": 72,
        "name": "aten::add_",
        "start_time": 1757354705985111626,
        "end_time": 1757354705985114826,
        "is_leaf": true,
        "scope": "forward",
        "parent": 71,
        "children": []
    },
    {
        "id": 73,
        "name": "aten::batch_norm",
        "start_time": 1757354705985122926,
        "end_time": 1757354705985168826,
        "is_leaf": true,
        "scope": "forward",
        "parent": 71,
        "children": []
    },
    {
        "id": 74,
        "name": "aten::add_",
        "start_time": 1757354705985172926,
        "end_time": 1757354705985177726,
        "is_leaf": true,
        "scope": "forward",
        "parent": 55,
        "children": []
    },
    {
        "id": 75,
        "name": "nn.Module: ReLU_3",
        "start_time": 1757354705985180426,
        "end_time": 1757354705985196326,
        "is_leaf": false,
        "scope": "forward",
        "parent": 55,
        "children": [
            76
        ]
    },
    {
        "id": 76,
        "name": "aten::relu_",
        "start_time": 1757354705985184726,
        "end_time": 1757354705985194926,
        "is_leaf": true,
        "scope": "forward",
        "parent": 75,
        "children": []
    },
    {
        "id": 77,
        "name": "nn.Module: Sequential_5",
        "start_time": 1757354705985202826,
        "end_time": 1757354705985571926,
        "is_leaf": false,
        "scope": "forward",
        "parent": 4,
        "children": [
            78
        ]
    },
    {
        "id": 78,
        "name": "nn.Module: BasicBlock_3",
        "start_time": 1757354705985205826,
        "end_time": 1757354705985571526,
        "is_leaf": false,
        "scope": "forward",
        "parent": 77,
        "children": [
            79,
            81,
            84,
            86,
            88,
            91,
            97,
            98
        ]
    },
    {
        "id": 79,
        "name": "nn.Module: Conv2d_9",
        "start_time": 1757354705985209326,
        "end_time": 1757354705985250226,
        "is_leaf": false,
        "scope": "forward",
        "parent": 78,
        "children": [
            80
        ]
    },
    {
        "id": 80,
        "name": "aten::conv2d",
        "start_time": 1757354705985215926,
        "end_time": 1757354705985248626,
        "is_leaf": true,
        "scope": "forward",
        "parent": 79,
        "children": []
    },
    {
        "id": 81,
        "name": "nn.Module: BatchNorm2d_9",
        "start_time": 1757354705985253026,
        "end_time": 1757354705985310426,
        "is_leaf": false,
        "scope": "forward",
        "parent": 78,
        "children": [
            82,
            83
        ]
    },
    {
        "id": 82,
        "name": "aten::add_",
        "start_time": 1757354705985259226,
        "end_time": 1757354705985262226,
        "is_leaf": true,
        "scope": "forward",
        "parent": 81,
        "children": []
    },
    {
        "id": 83,
        "name": "aten::batch_norm",
        "start_time": 1757354705985271226,
        "end_time": 1757354705985308926,
        "is_leaf": true,
        "scope": "forward",
        "parent": 81,
        "children": []
    },
    {
        "id": 84,
        "name": "nn.Module: ReLU_4",
        "start_time": 1757354705985312326,
        "end_time": 1757354705985325726,
        "is_leaf": false,
        "scope": "forward",
        "parent": 78,
        "children": [
            85
        ]
    },
    {
        "id": 85,
        "name": "aten::relu_",
        "start_time": 1757354705985316026,
        "end_time": 1757354705985323926,
        "is_leaf": true,
        "scope": "forward",
        "parent": 84,
        "children": []
    },
    {
        "id": 86,
        "name": "nn.Module: Conv2d_10",
        "start_time": 1757354705985327726,
        "end_time": 1757354705985375926,
        "is_leaf": false,
        "scope": "forward",
        "parent": 78,
        "children": [
            87
        ]
    },
    {
        "id": 87,
        "name": "aten::conv2d",
        "start_time": 1757354705985333426,
        "end_time": 1757354705985374026,
        "is_leaf": true,
        "scope": "forward",
        "parent": 86,
        "children": []
    },
    {
        "id": 88,
        "name": "nn.Module: BatchNorm2d_10",
        "start_time": 1757354705985378526,
        "end_time": 1757354705985443826,
        "is_leaf": false,
        "scope": "forward",
        "parent": 78,
        "children": [
            89,
            90
        ]
    },
    {
        "id": 89,
        "name": "aten::add_",
        "start_time": 1757354705985385426,
        "end_time": 1757354705985388726,
        "is_leaf": true,
        "scope": "forward",
        "parent": 88,
        "children": []
    },
    {
        "id": 90,
        "name": "aten::batch_norm",
        "start_time": 1757354705985404026,
        "end_time": 1757354705985442426,
        "is_leaf": true,
        "scope": "forward",
        "parent": 88,
        "children": []
    },
    {
        "id": 91,
        "name": "nn.Module: Sequential_6",
        "start_time": 1757354705985446226,
        "end_time": 1757354705985547826,
        "is_leaf": false,
        "scope": "forward",
        "parent": 78,
        "children": [
            92,
            94
        ]
    },
    {
        "id": 92,
        "name": "nn.Module: Conv2d_11",
        "start_time": 1757354705985449826,
        "end_time": 1757354705985486826,
        "is_leaf": false,
        "scope": "forward",
        "parent": 91,
        "children": [
            93
        ]
    },
    {
        "id": 93,
        "name": "aten::conv2d",
        "start_time": 1757354705985455726,
        "end_time": 1757354705985485226,
        "is_leaf": true,
        "scope": "forward",
        "parent": 92,
        "children": []
    },
    {
        "id": 94,
        "name": "nn.Module: BatchNorm2d_11",
        "start_time": 1757354705985488926,
        "end_time": 1757354705985547226,
        "is_leaf": false,
        "scope": "forward",
        "parent": 91,
        "children": [
            95,
            96
        ]
    },
    {
        "id": 95,
        "name": "aten::add_",
        "start_time": 1757354705985495226,
        "end_time": 1757354705985498426,
        "is_leaf": true,
        "scope": "forward",
        "parent": 94,
        "children": []
    },
    {
        "id": 96,
        "name": "aten::batch_norm",
        "start_time": 1757354705985506826,
        "end_time": 1757354705985545826,
        "is_leaf": true,
        "scope": "forward",
        "parent": 94,
        "children": []
    },
    {
        "id": 97,
        "name": "aten::add_",
        "start_time": 1757354705985549826,
        "end_time": 1757354705985554726,
        "is_leaf": true,
        "scope": "forward",
        "parent": 78,
        "children": []
    },
    {
        "id": 98,
        "name": "nn.Module: ReLU_4",
        "start_time": 1757354705985557126,
        "end_time": 1757354705985569826,
        "is_leaf": false,
        "scope": "forward",
        "parent": 78,
        "children": [
            99
        ]
    },
    {
        "id": 99,
        "name": "aten::relu_",
        "start_time": 1757354705985560826,
        "end_time": 1757354705985568626,
        "is_leaf": true,
        "scope": "forward",
        "parent": 98,
        "children": []
    },
    {
        "id": 100,
        "name": "nn.Module: AdaptiveAvgPool2d_0",
        "start_time": 1757354705985583026,
        "end_time": 1757354705985627726,
        "is_leaf": false,
        "scope": "forward",
        "parent": 4,
        "children": [
            101
        ]
    },
    {
        "id": 101,
        "name": "aten::adaptive_avg_pool2d",
        "start_time": 1757354705985604426,
        "end_time": 1757354705985625826,
        "is_leaf": true,
        "scope": "forward",
        "parent": 100,
        "children": []
    },
    {
        "id": 102,
        "name": "aten::flatten",
        "start_time": 1757354705985648026,
        "end_time": 1757354705985655826,
        "is_leaf": true,
        "scope": "forward",
        "parent": 4,
        "children": []
    },
    {
        "id": 103,
        "name": "nn.Module: Linear_0",
        "start_time": 1757354705985662426,
        "end_time": 1757354705985734726,
        "is_leaf": false,
        "scope": "forward",
        "parent": 4,
        "children": [
            104
        ]
    },
    {
        "id": 104,
        "name": "aten::linear",
        "start_time": 1757354705985669926,
        "end_time": 1757354705985732426,
        "is_leaf": true,
        "scope": "forward",
        "parent": 103,
        "children": []
    },
    {
        "id": 105,
        "name": "nn.Module: CrossEntropyLoss_0",
        "start_time": 1757354705985739826,
        "end_time": 1757354705985812426,
        "is_leaf": false,
        "scope": "forward",
        "parent": null,
        "children": [
            106
        ]
    },
    {
        "id": 106,
        "name": "aten::cross_entropy_loss",
        "start_time": 1757354705985760626,
        "end_time": 1757354705985810526,
        "is_leaf": true,
        "scope": "forward",
        "parent": 105,
        "children": []
    },
    {
        "id": 107,
        "name": "aten::ones_like",
        "start_time": 1757354705985864226,
        "end_time": 1757354705985880426,
        "is_leaf": true,
        "scope": "forward",
        "parent": null,
        "children": []
    },
    {
        "id": 108,
        "name": "NllLossBackward0",
        "start_time": 1757354705993236926,
        "end_time": 1757354705993292326,
        "is_leaf": true,
        "scope": "backward",
        "parent": null,
        "children": []
    },
    {
        "id": 109,
        "name": "LogSoftmaxBackward0",
        "start_time": 1757354705993311626,
        "end_time": 1757354705993327226,
        "is_leaf": true,
        "scope": "backward",
        "parent": null,
        "children": []
    },
    {
        "id": 110,
        "name": "AddmmBackward0",
        "start_time": 1757354705993357826,
        "end_time": 1757354705993436426,
        "is_leaf": true,
        "scope": "backward",
        "parent": null,
        "children": []
    },
    {
        "id": 111,
        "name": "aten::sum",
        "start_time": 1757354705993439726,
        "end_time": 1757354705993450926,
        "is_leaf": true,
        "scope": "backward",
        "parent": null,
        "children": []
    },
    {
        "id": 112,
        "name": "aten::view",
        "start_time": 1757354705993453726,
        "end_time": 1757354705993456526,
        "is_leaf": true,
        "scope": "backward",
        "parent": null,
        "children": []
    },
    {
        "id": 113,
        "name": "torch::autograd::AccumulateGrad",
        "start_time": 1757354705993482126,
        "end_time": 1757354705993492726,
        "is_leaf": true,
        "scope": "backward",
        "parent": null,
        "children": []
    },
    {
        "id": 114,
        "name": "TBackward0",
        "start_time": 1757354705993500826,
        "end_time": 1757354705993508826,
        "is_leaf": true,
        "scope": "backward",
        "parent": null,
        "children": []
    },
    {
        "id": 115,
        "name": "torch::autograd::AccumulateGrad",
        "start_time": 1757354705993516126,
        "end_time": 1757354705993521226,
        "is_leaf": true,
        "scope": "backward",
        "parent": null,
        "children": []
    },
    {
        "id": 116,
        "name": "ViewBackward0",
        "start_time": 1757354705993527326,
        "end_time": 1757354705993538526,
        "is_leaf": true,
        "scope": "backward",
        "parent": null,
        "children": []
    },
    {
        "id": 117,
        "name": "MeanBackward1",
        "start_time": 1757354705993548626,
        "end_time": 1757354705993588126,
        "is_leaf": true,
        "scope": "backward",
        "parent": null,
        "children": []
    },
    {
        "id": 118,
        "name": "ReluBackward0",
        "start_time": 1757354705993597126,
        "end_time": 1757354705993621526,
        "is_leaf": true,
        "scope": "backward",
        "parent": null,
        "children": []
    },
    {
        "id": 119,
        "name": "AddBackward0",
        "start_time": 1757354705993630326,
        "end_time": 1757354705993630826,
        "is_leaf": true,
        "scope": "backward",
        "parent": null,
        "children": []
    },
    {
        "id": 120,
        "name": "CudnnBatchNormBackward0",
        "start_time": 1757354705993639826,
        "end_time": 1757354705993686226,
        "is_leaf": true,
        "scope": "backward",
        "parent": null,
        "children": []
    },
    {
        "id": 121,
        "name": "torch::autograd::AccumulateGrad",
        "start_time": 1757354705993697926,
        "end_time": 1757354705993703926,
        "is_leaf": true,
        "scope": "backward",
        "parent": null,
        "children": []
    },
    {
        "id": 122,
        "name": "torch::autograd::AccumulateGrad",
        "start_time": 1757354705993711626,
        "end_time": 1757354705993716826,
        "is_leaf": true,
        "scope": "backward",
        "parent": null,
        "children": []
    },
    {
        "id": 123,
        "name": "ConvolutionBackward0",
        "start_time": 1757354705993724326,
        "end_time": 1757354705993852026,
        "is_leaf": true,
        "scope": "backward",
        "parent": null,
        "children": []
    },
    {
        "id": 124,
        "name": "torch::autograd::AccumulateGrad",
        "start_time": 1757354705993864126,
        "end_time": 1757354705993870526,
        "is_leaf": true,
        "scope": "backward",
        "parent": null,
        "children": []
    },
    {
        "id": 125,
        "name": "CudnnBatchNormBackward0",
        "start_time": 1757354705993879126,
        "end_time": 1757354705993911926,
        "is_leaf": true,
        "scope": "backward",
        "parent": null,
        "children": []
    },
    {
        "id": 126,
        "name": "torch::autograd::AccumulateGrad",
        "start_time": 1757354705993923426,
        "end_time": 1757354705993928526,
        "is_leaf": true,
        "scope": "backward",
        "parent": null,
        "children": []
    },
    {
        "id": 127,
        "name": "torch::autograd::AccumulateGrad",
        "start_time": 1757354705993934626,
        "end_time": 1757354705993939226,
        "is_leaf": true,
        "scope": "backward",
        "parent": null,
        "children": []
    },
    {
        "id": 128,
        "name": "ConvolutionBackward0",
        "start_time": 1757354705993946126,
        "end_time": 1757354705994007526,
        "is_leaf": true,
        "scope": "backward",
        "parent": null,
        "children": []
    },
    {
        "id": 129,
        "name": "torch::autograd::AccumulateGrad",
        "start_time": 1757354705994017426,
        "end_time": 1757354705994022826,
        "is_leaf": true,
        "scope": "backward",
        "parent": null,
        "children": []
    },
    {
        "id": 130,
        "name": "ReluBackward0",
        "start_time": 1757354705994029426,
        "end_time": 1757354705994042826,
        "is_leaf": true,
        "scope": "backward",
        "parent": null,
        "children": []
    },
    {
        "id": 131,
        "name": "CudnnBatchNormBackward0",
        "start_time": 1757354705994052026,
        "end_time": 1757354705994115926,
        "is_leaf": true,
        "scope": "backward",
        "parent": null,
        "children": []
    },
    {
        "id": 132,
        "name": "torch::autograd::AccumulateGrad",
        "start_time": 1757354705994126526,
        "end_time": 1757354705994131726,
        "is_leaf": true,
        "scope": "backward",
        "parent": null,
        "children": []
    },
    {
        "id": 133,
        "name": "torch::autograd::AccumulateGrad",
        "start_time": 1757354705994138126,
        "end_time": 1757354705994142926,
        "is_leaf": true,
        "scope": "backward",
        "parent": null,
        "children": []
    },
    {
        "id": 134,
        "name": "ConvolutionBackward0",
        "start_time": 1757354705994149326,
        "end_time": 1757354705994197626,
        "is_leaf": true,
        "scope": "backward",
        "parent": null,
        "children": []
    },
    {
        "id": 135,
        "name": "aten::add_",
        "start_time": 1757354705994203026,
        "end_time": 1757354705994210226,
        "is_leaf": true,
        "scope": "backward",
        "parent": null,
        "children": []
    },
    {
        "id": 136,
        "name": "torch::autograd::AccumulateGrad",
        "start_time": 1757354705994219126,
        "end_time": 1757354705994226126,
        "is_leaf": true,
        "scope": "backward",
        "parent": null,
        "children": []
    },
    {
        "id": 137,
        "name": "ReluBackward0",
        "start_time": 1757354705994232826,
        "end_time": 1757354705994240826,
        "is_leaf": true,
        "scope": "backward",
        "parent": null,
        "children": []
    },
    {
        "id": 138,
        "name": "AddBackward0",
        "start_time": 1757354705994248826,
        "end_time": 1757354705994249326,
        "is_leaf": true,
        "scope": "backward",
        "parent": null,
        "children": []
    },
    {
        "id": 139,
        "name": "CudnnBatchNormBackward0",
        "start_time": 1757354705994256026,
        "end_time": 1757354705994283026,
        "is_leaf": true,
        "scope": "backward",
        "parent": null,
        "children": []
    },
    {
        "id": 140,
        "name": "torch::autograd::AccumulateGrad",
        "start_time": 1757354705994293326,
        "end_time": 1757354705994298326,
        "is_leaf": true,
        "scope": "backward",
        "parent": null,
        "children": []
    },
    {
        "id": 141,
        "name": "torch::autograd::AccumulateGrad",
        "start_time": 1757354705994304626,
        "end_time": 1757354705994309126,
        "is_leaf": true,
        "scope": "backward",
        "parent": null,
        "children": []
    },
    {
        "id": 142,
        "name": "ConvolutionBackward0",
        "start_time": 1757354705994314926,
        "end_time": 1757354705994355626,
        "is_leaf": true,
        "scope": "backward",
        "parent": null,
        "children": []
    },
    {
        "id": 143,
        "name": "torch::autograd::AccumulateGrad",
        "start_time": 1757354705994364426,
        "end_time": 1757354705994372926,
        "is_leaf": true,
        "scope": "backward",
        "parent": null,
        "children": []
    },
    {
        "id": 144,
        "name": "CudnnBatchNormBackward0",
        "start_time": 1757354705994379026,
        "end_time": 1757354705994404626,
        "is_leaf": true,
        "scope": "backward",
        "parent": null,
        "children": []
    },
    {
        "id": 145,
        "name": "torch::autograd::AccumulateGrad",
        "start_time": 1757354705994414426,
        "end_time": 1757354705994419226,
        "is_leaf": true,
        "scope": "backward",
        "parent": null,
        "children": []
    },
    {
        "id": 146,
        "name": "torch::autograd::AccumulateGrad",
        "start_time": 1757354705994425226,
        "end_time": 1757354705994429926,
        "is_leaf": true,
        "scope": "backward",
        "parent": null,
        "children": []
    },
    {
        "id": 147,
        "name": "ConvolutionBackward0",
        "start_time": 1757354705994436026,
        "end_time": 1757354705994473926,
        "is_leaf": true,
        "scope": "backward",
        "parent": null,
        "children": []
    },
    {
        "id": 148,
        "name": "torch::autograd::AccumulateGrad",
        "start_time": 1757354705994482926,
        "end_time": 1757354705994488126,
        "is_leaf": true,
        "scope": "backward",
        "parent": null,
        "children": []
    },
    {
        "id": 149,
        "name": "ReluBackward0",
        "start_time": 1757354705994494526,
        "end_time": 1757354705994504026,
        "is_leaf": true,
        "scope": "backward",
        "parent": null,
        "children": []
    },
    {
        "id": 150,
        "name": "CudnnBatchNormBackward0",
        "start_time": 1757354705994516126,
        "end_time": 1757354705994542226,
        "is_leaf": true,
        "scope": "backward",
        "parent": null,
        "children": []
    },
    {
        "id": 151,
        "name": "torch::autograd::AccumulateGrad",
        "start_time": 1757354705994552326,
        "end_time": 1757354705994557826,
        "is_leaf": true,
        "scope": "backward",
        "parent": null,
        "children": []
    },
    {
        "id": 152,
        "name": "torch::autograd::AccumulateGrad",
        "start_time": 1757354705994564026,
        "end_time": 1757354705994568326,
        "is_leaf": true,
        "scope": "backward",
        "parent": null,
        "children": []
    },
    {
        "id": 153,
        "name": "ConvolutionBackward0",
        "start_time": 1757354705994574826,
        "end_time": 1757354705994611626,
        "is_leaf": true,
        "scope": "backward",
        "parent": null,
        "children": []
    },
    {
        "id": 154,
        "name": "aten::add_",
        "start_time": 1757354705994616226,
        "end_time": 1757354705994620726,
        "is_leaf": true,
        "scope": "backward",
        "parent": null,
        "children": []
    },
    {
        "id": 155,
        "name": "torch::autograd::AccumulateGrad",
        "start_time": 1757354705994629026,
        "end_time": 1757354705994633726,
        "is_leaf": true,
        "scope": "backward",
        "parent": null,
        "children": []
    },
    {
        "id": 156,
        "name": "ReluBackward0",
        "start_time": 1757354705994639926,
        "end_time": 1757354705994648426,
        "is_leaf": true,
        "scope": "backward",
        "parent": null,
        "children": []
    },
    {
        "id": 157,
        "name": "AddBackward0",
        "start_time": 1757354705994655726,
        "end_time": 1757354705994656226,
        "is_leaf": true,
        "scope": "backward",
        "parent": null,
        "children": []
    },
    {
        "id": 158,
        "name": "CudnnBatchNormBackward0",
        "start_time": 1757354705994662826,
        "end_time": 1757354705994691026,
        "is_leaf": true,
        "scope": "backward",
        "parent": null,
        "children": []
    },
    {
        "id": 159,
        "name": "torch::autograd::AccumulateGrad",
        "start_time": 1757354705994700626,
        "end_time": 1757354705994705526,
        "is_leaf": true,
        "scope": "backward",
        "parent": null,
        "children": []
    },
    {
        "id": 160,
        "name": "torch::autograd::AccumulateGrad",
        "start_time": 1757354705994711526,
        "end_time": 1757354705994716226,
        "is_leaf": true,
        "scope": "backward",
        "parent": null,
        "children": []
    },
    {
        "id": 161,
        "name": "ConvolutionBackward0",
        "start_time": 1757354705994724326,
        "end_time": 1757354705994762426,
        "is_leaf": true,
        "scope": "backward",
        "parent": null,
        "children": []
    },
    {
        "id": 162,
        "name": "torch::autograd::AccumulateGrad",
        "start_time": 1757354705994770426,
        "end_time": 1757354705994775826,
        "is_leaf": true,
        "scope": "backward",
        "parent": null,
        "children": []
    },
    {
        "id": 163,
        "name": "CudnnBatchNormBackward0",
        "start_time": 1757354705994782326,
        "end_time": 1757354705994830826,
        "is_leaf": true,
        "scope": "backward",
        "parent": null,
        "children": []
    },
    {
        "id": 164,
        "name": "torch::autograd::AccumulateGrad",
        "start_time": 1757354705994841026,
        "end_time": 1757354705994845826,
        "is_leaf": true,
        "scope": "backward",
        "parent": null,
        "children": []
    },
    {
        "id": 165,
        "name": "torch::autograd::AccumulateGrad",
        "start_time": 1757354705994904126,
        "end_time": 1757354705994909026,
        "is_leaf": true,
        "scope": "backward",
        "parent": null,
        "children": []
    },
    {
        "id": 166,
        "name": "ConvolutionBackward0",
        "start_time": 1757354705994916526,
        "end_time": 1757354705994961526,
        "is_leaf": true,
        "scope": "backward",
        "parent": null,
        "children": []
    },
    {
        "id": 167,
        "name": "torch::autograd::AccumulateGrad",
        "start_time": 1757354705994971126,
        "end_time": 1757354705994976126,
        "is_leaf": true,
        "scope": "backward",
        "parent": null,
        "children": []
    },
    {
        "id": 168,
        "name": "ReluBackward0",
        "start_time": 1757354705994982426,
        "end_time": 1757354705994993226,
        "is_leaf": true,
        "scope": "backward",
        "parent": null,
        "children": []
    },
    {
        "id": 169,
        "name": "CudnnBatchNormBackward0",
        "start_time": 1757354705995000626,
        "end_time": 1757354705995028226,
        "is_leaf": true,
        "scope": "backward",
        "parent": null,
        "children": []
    },
    {
        "id": 170,
        "name": "torch::autograd::AccumulateGrad",
        "start_time": 1757354705995037826,
        "end_time": 1757354705995043126,
        "is_leaf": true,
        "scope": "backward",
        "parent": null,
        "children": []
    },
    {
        "id": 171,
        "name": "torch::autograd::AccumulateGrad",
        "start_time": 1757354705995049326,
        "end_time": 1757354705995054126,
        "is_leaf": true,
        "scope": "backward",
        "parent": null,
        "children": []
    },
    {
        "id": 172,
        "name": "ConvolutionBackward0",
        "start_time": 1757354705995064826,
        "end_time": 1757354705995105226,
        "is_leaf": true,
        "scope": "backward",
        "parent": null,
        "children": []
    },
    {
        "id": 173,
        "name": "aten::add_",
        "start_time": 1757354705995109426,
        "end_time": 1757354705995116826,
        "is_leaf": true,
        "scope": "backward",
        "parent": null,
        "children": []
    },
    {
        "id": 174,
        "name": "torch::autograd::AccumulateGrad",
        "start_time": 1757354705995125626,
        "end_time": 1757354705995130726,
        "is_leaf": true,
        "scope": "backward",
        "parent": null,
        "children": []
    },
    {
        "id": 175,
        "name": "ReluBackward0",
        "start_time": 1757354705995136826,
        "end_time": 1757354705995143726,
        "is_leaf": true,
        "scope": "backward",
        "parent": null,
        "children": []
    },
    {
        "id": 176,
        "name": "AddBackward0",
        "start_time": 1757354705995151426,
        "end_time": 1757354705995151926,
        "is_leaf": true,
        "scope": "backward",
        "parent": null,
        "children": []
    },
    {
        "id": 177,
        "name": "CudnnBatchNormBackward0",
        "start_time": 1757354705995159226,
        "end_time": 1757354705995185526,
        "is_leaf": true,
        "scope": "backward",
        "parent": null,
        "children": []
    },
    {
        "id": 178,
        "name": "torch::autograd::AccumulateGrad",
        "start_time": 1757354705995194826,
        "end_time": 1757354705995201526,
        "is_leaf": true,
        "scope": "backward",
        "parent": null,
        "children": []
    },
    {
        "id": 179,
        "name": "torch::autograd::AccumulateGrad",
        "start_time": 1757354705995207826,
        "end_time": 1757354705995212226,
        "is_leaf": true,
        "scope": "backward",
        "parent": null,
        "children": []
    },
    {
        "id": 180,
        "name": "ConvolutionBackward0",
        "start_time": 1757354705995218026,
        "end_time": 1757354705995260126,
        "is_leaf": true,
        "scope": "backward",
        "parent": null,
        "children": []
    },
    {
        "id": 181,
        "name": "torch::autograd::AccumulateGrad",
        "start_time": 1757354705995268826,
        "end_time": 1757354705995273926,
        "is_leaf": true,
        "scope": "backward",
        "parent": null,
        "children": []
    },
    {
        "id": 182,
        "name": "ReluBackward0",
        "start_time": 1757354705995280026,
        "end_time": 1757354705995286826,
        "is_leaf": true,
        "scope": "backward",
        "parent": null,
        "children": []
    },
    {
        "id": 183,
        "name": "CudnnBatchNormBackward0",
        "start_time": 1757354705995294726,
        "end_time": 1757354705995322826,
        "is_leaf": true,
        "scope": "backward",
        "parent": null,
        "children": []
    },
    {
        "id": 184,
        "name": "torch::autograd::AccumulateGrad",
        "start_time": 1757354705995333026,
        "end_time": 1757354705995338026,
        "is_leaf": true,
        "scope": "backward",
        "parent": null,
        "children": []
    },
    {
        "id": 185,
        "name": "torch::autograd::AccumulateGrad",
        "start_time": 1757354705995344626,
        "end_time": 1757354705995349726,
        "is_leaf": true,
        "scope": "backward",
        "parent": null,
        "children": []
    },
    {
        "id": 186,
        "name": "ConvolutionBackward0",
        "start_time": 1757354705995355826,
        "end_time": 1757354705995387926,
        "is_leaf": true,
        "scope": "backward",
        "parent": null,
        "children": []
    },
    {
        "id": 187,
        "name": "aten::add_",
        "start_time": 1757354705995392226,
        "end_time": 1757354705995395326,
        "is_leaf": true,
        "scope": "backward",
        "parent": null,
        "children": []
    },
    {
        "id": 188,
        "name": "torch::autograd::AccumulateGrad",
        "start_time": 1757354705995403226,
        "end_time": 1757354705995408326,
        "is_leaf": true,
        "scope": "backward",
        "parent": null,
        "children": []
    },
    {
        "id": 189,
        "name": "MaxPool2DWithIndicesBackward0",
        "start_time": 1757354705995415026,
        "end_time": 1757354705995440326,
        "is_leaf": true,
        "scope": "backward",
        "parent": null,
        "children": []
    },
    {
        "id": 190,
        "name": "ReluBackward0",
        "start_time": 1757354705995448326,
        "end_time": 1757354705995455526,
        "is_leaf": true,
        "scope": "backward",
        "parent": null,
        "children": []
    },
    {
        "id": 191,
        "name": "CudnnBatchNormBackward0",
        "start_time": 1757354705995468126,
        "end_time": 1757354705995497826,
        "is_leaf": true,
        "scope": "backward",
        "parent": null,
        "children": []
    },
    {
        "id": 192,
        "name": "torch::autograd::AccumulateGrad",
        "start_time": 1757354705995507726,
        "end_time": 1757354705995512226,
        "is_leaf": true,
        "scope": "backward",
        "parent": null,
        "children": []
    },
    {
        "id": 193,
        "name": "torch::autograd::AccumulateGrad",
        "start_time": 1757354705995518326,
        "end_time": 1757354705995522626,
        "is_leaf": true,
        "scope": "backward",
        "parent": null,
        "children": []
    },
    {
        "id": 194,
        "name": "ConvolutionBackward0",
        "start_time": 1757354705995529926,
        "end_time": 1757354705995560126,
        "is_leaf": true,
        "scope": "backward",
        "parent": null,
        "children": []
    },
    {
        "id": 195,
        "name": "torch::autograd::AccumulateGrad",
        "start_time": 1757354705995568526,
        "end_time": 1757354705995573426,
        "is_leaf": true,
        "scope": "backward",
        "parent": null,
        "children": []
    },
    {
        "id": 201,
        "name": "aten::_foreach_lerp_",
        "start_time": 1757354705996112826,
        "end_time": 1757354705996137326,
        "is_leaf": true,
        "scope": "postprocess",
        "parent": null,
        "children": []
    },
    {
        "id": 202,
        "name": "aten::_foreach_mul_",
        "start_time": 1757354705996149026,
        "end_time": 1757354705996242526,
        "is_leaf": true,
        "scope": "postprocess",
        "parent": null,
        "children": []
    },
    {
        "id": 203,
        "name": "aten::_foreach_addcmul_",
        "start_time": 1757354705996258026,
        "end_time": 1757354705996403226,
        "is_leaf": true,
        "scope": "postprocess",
        "parent": null,
        "children": []
    },
    {
        "id": 280,
        "name": "aten::_foreach_sqrt",
        "start_time": 1757354705996960926,
        "end_time": 1757354705997122226,
        "is_leaf": true,
        "scope": "postprocess",
        "parent": null,
        "children": []
    },
    {
        "id": 281,
        "name": "aten::_foreach_div_",
        "start_time": 1757354705997155126,
        "end_time": 1757354705997237526,
        "is_leaf": true,
        "scope": "postprocess",
        "parent": null,
        "children": []
    },
    {
        "id": 282,
        "name": "aten::_foreach_add_",
        "start_time": 1757354705997245126,
        "end_time": 1757354705997356626,
        "is_leaf": true,
        "scope": "postprocess",
        "parent": null,
        "children": []
    },
    {
        "id": 283,
        "name": "aten::_foreach_addcdiv_",
        "start_time": 1757354705997493426,
        "end_time": 1757354705997595426,
        "is_leaf": true,
        "scope": "postprocess",
        "parent": null,
        "children": []
    }
]